{"docker_docker概述.md":"msCyYOol","go_go语言之nil.md":"CAdNlf0d","docker_面试问题.md":"BcWPXlPs","docker_docker项目部署.md":"B55Ko7WL","go_bug总结.md":"C4NMu1pP","go_gorm.md":"BIP4skm-","go_go语言之常用库函数.md":"v3heoruj","go_go语言之垃圾回收.md":"aYS8Cmrb","go_go算法模板.md":"DoEmXHD-","gorm_association.md":"BylQ-vRj","go_go语言之常见面试题.md":"DY0G8U11","设计模式_面试问题.md":"WJxCLYFT","linux_linux常用指令.md":"CuVgWkRH","go_template模板.md":"COIyyewR","go_go语言之文件读写.md":"DbhVNYlk","k8s_第一章 k8s介绍.md":"BQaqcpK7","go_go语言之基础知识.md":"CQpX5yaF","redis_redis集群.md":"v_d3q03V","hddb_raft问题.md":"36xtvkc_","go_go语言之编译.md":"o__qSqUL","mysql_面试问题.md":"cfpDflnm","redis_redis之数据结构.md":"CLAns0tk","hddb_mapreduce.md":"Boi85PB2","redis_redis之数据类型.md":"DDxcBevX","shell_awk.md":"_yYKLlGD","计算机网络_http.md":"BGrqFbpA","mysql_配置.md":"BLsJwUSM","mysql_基础篇.md":"DxARJaIA","go_违反直觉.md":"COBuSlR2","docker_docker基础知识.md":"C_5xI6Y-","hddb_raft.md":"Ccu61bZ7","mysql_锁.md":"CwP7vyCA","go_go语言之数组与切片.md":"BEgZl5Kv","k8s_第三章 资源管理.md":"BE-CePRC","index.md":"JiVFEvUa","mysql_数据库安全.md":"CpGxdIDs","操作系统_多线程编程.md":"s_Lq1H19","k8s_常用指令.md":"Sbubu5Jy","操作系统_硬件结构.md":"PRH0rMog","go_go语言之并发编程.md":"C1bsSQxW","redis_redis持久化.md":"44BoIn9f","计算机网络_tcp.md":"CbsZtCEn","redis_面试问题.md":"CMwDjQhc","go_go语言之unsafe.md":"COXFYBlY","操作系统_面试问题.md":"Rg4_XmCc","go_go语言之调度器.md":"NtAL_QLc","go_go语言资料.md":"BakAkqbY","mysql_sql操作.md":"QBDL3bNV","go_go语言之通道.md":"WaDK3u_8","计算机网络_rpc.md":"B35AwY2J","go_go语言之map.md":"C1zaNeum","about.md":"CUN1EXL5","redis_redis之通信协议.md":"B0yjanJ3","操作系统_进程线程协程.md":"BuNPozpm","docker_docker常用命令.md":"DXBWlpWX","go_gin.md":"Cm7PR230","计算机网络_面试问题.md":"D6mmryEu","go_go语言之接口.md":"C0_srq5s","k8s_第十章 dashboard.md":"CO6OwAXk","k8s_第二章 集群环境搭建.md":"B8kU3O5g","k8s_第九章 安全认证.md":"DeETxKjJ","linux_面试问题.md":"yIzBGA5A","python_venv.md":"aM7wB5oT","redis_redis之内存回收.md":"DSYw8qcI","mysql_url.md":"BQID5IA1","linux_高频考点.md":"4SdiGPuI","mysql_日志.md":"0nNrXSdY","计算机网络_socket.md":"Kgyk5g8P","k8s_第七章 service详解.md":"EbNnY5pO","go_go语言之反射.md":"BJBm7Xhm","go_go语言之context.md":"BM-V89Dq","hddb_cap.md":"Bryu5U01","redis_redis之网络模型.md":"CqXRpSk6","k8s_第八章 数据存储.md":"CXtrLJbg","k8s_第四章 实战入门.md":"DYx7CvrB","redis_redis锁.md":"D1No5GDB","k8s_第五章 pod详解.md":"B46rvisp","k8s_第六章 pod控制器详解.md":"CCoHpbBL"}
